[
    {
        "classes": [
            {
                "className": "DatabaseController",
                "object": true,
                "qualifiedClassName": "DatabaseController",
                "superClasses": [
                    {
                        "access": "public",
                        "name": "QObject"
                    }
                ]
            }
        ],
        "inputFile": "databasecontroller.h",
        "outputRevision": 68
    },
    {
        "classes": [
            {
                "className": "GameLogic",
                "object": true,
                "qualifiedClassName": "GameLogic",
                "superClasses": [
                    {
                        "access": "public",
                        "name": "QObject"
                    }
                ]
            }
        ],
        "inputFile": "gamelogic.h",
        "outputRevision": 68
    },
    {
        "classes": [
            {
                "className": "PlayerManger",
                "object": true,
                "qualifiedClassName": "PlayerManger",
                "superClasses": [
                    {
                        "access": "public",
                        "name": "QObject"
                    }
                ]
            }
        ],
        "inputFile": "playermanger.h",
        "outputRevision": 68
    }
]
